pyark/__init__.py
pyark/backoff_retrier.py
pyark/cva_client.py
pyark/errors.py
pyark/rest_client.py
pyark/tests.py
pyark/models/__init__.py
pyark/models/wrappers.py
pyark/subclients/__init__.py
pyark/subclients/cases_client.py
pyark/subclients/data_intake_client.py
pyark/subclients/entities_client.py
pyark/subclients/evidences_client.py
pyark/subclients/lift_over_client.py
pyark/subclients/report_events_client.py
pyark/subclients/transactions_client.py
pyark/subclients/variants_client.py
clinical_variant_ark-5.0.1.dist-info/LICENSE
clinical_variant_ark-5.0.1.dist-info/METADATA
clinical_variant_ark-5.0.1.dist-info/WHEEL
clinical_variant_ark-5.0.1.dist-info/top_level.txt
clinical_variant_ark-5.0.1.dist-info/RECORD
